setup.py
statusik/__init__.py
statusik/statusik.py
statusik.egg-info/PKG-INFO
statusik.egg-info/SOURCES.txt
statusik.egg-info/dependency_links.txt
statusik.egg-info/not-zip-safe
statusik.egg-info/top_level.txt