Metadata-Version: 1.0
Name: statusik
Version: 0.0.2
Summary: Yet another tool for feeding i3bar ...
Home-page: https://bitbucket.org/cepe/statusik
Author: Paweł Chwała
Author-email: pawel.chwala@gmail.com
License: MIT
Platform: UNKNOWN
